spanda/__init__.py
spanda/_modidx.py
spanda/readers.py
spanda/sig.py
spanda/utils.py
spanda/data/__init__.py
spanda/data/transforms.py
spanda/data/external/__init__.py
spanda/data/external/kssl.py
spanda/data/external/lucas.py
spanda/data/external/wcrc.py
spanda/miniai/__init__.py
spanda/miniai/activations.py
spanda/miniai/augment.py
spanda/miniai/conv.py
spanda/miniai/datasets.py
spanda/miniai/init.py
spanda/miniai/learner.py
spanda/miniai/resnet.py
spanda/miniai/sgd.py
spanda/miniai/training.py
spanda-0.0.17.dist-info/LICENSE
spanda-0.0.17.dist-info/METADATA
spanda-0.0.17.dist-info/WHEEL
spanda-0.0.17.dist-info/entry_points.txt
spanda-0.0.17.dist-info/top_level.txt
spanda-0.0.17.dist-info/RECORD
