Metadata-Version: 2.1
Name: spanda
Version: 0.0.17
Summary: Utilities to do research in soil spectroscopy harnessing the fastai framework and mindset
Home-page: https://github.com/franckalbinet/spanda
Author: Franck Albinet
Author-email: franckalbinet@gmail.com
License: Apache Software License 2.0
Keywords: nbdev jupyter notebook python
Classifier: Development Status :: 4 - Beta
Classifier: Intended Audience :: Developers
Classifier: Natural Language :: English
Classifier: Programming Language :: Python :: 3.7
Classifier: Programming Language :: Python :: 3.8
Classifier: Programming Language :: Python :: 3.9
Classifier: Programming Language :: Python :: 3.10
Classifier: License :: OSI Approved :: Apache Software License
Requires-Python: >=3.7
License-File: LICENSE
Requires-Dist: fastai
Requires-Dist: pandas
Requires-Dist: matplotlib
Requires-Dist: brukeropusreader
Requires-Dist: openpyxl
Requires-Dist: kennard-stone
Requires-Dist: timm
Requires-Dist: specdal
Requires-Dist: torch (<2.1,>=1.7)
Requires-Dist: torcheval
Requires-Dist: diffusers
Requires-Dist: einops
Requires-Dist: datasets
Provides-Extra: dev
